tinyblock/__init__.py
tinyblock/core.py
tinyblock-0.2.0.dist-info/DESCRIPTION.rst
tinyblock-0.2.0.dist-info/METADATA
tinyblock-0.2.0.dist-info/RECORD
tinyblock-0.2.0.dist-info/WHEEL
tinyblock-0.2.0.dist-info/metadata.json
tinyblock-0.2.0.dist-info/top_level.txt
