Metadata-Version: 2.0
Name: tinyblock
Version: 0.2.0
Summary: A simple blockchain package.
Home-page: https://github.com/zshvvhm/tinyblock
Author: zshvvhm
Author-email: zshvvhm95@gmail.com
License: MIT
Project-URL: Source, https://github.com/zshvvhm/tinyblock
Project-URL: Bug Reports, https://github.com/zshvvhm/tinyblock/issues
Keywords: simple tiny blockchain
Platform: UNKNOWN
Classifier: Topic :: Software Development
Classifier: License :: OSI Approved :: MIT License
Classifier: Programming Language :: Python :: 2
Classifier: Programming Language :: Python :: 2.6
Classifier: Programming Language :: Python :: 2.7
Classifier: Programming Language :: Python :: 3
Classifier: Programming Language :: Python :: 3.3
Classifier: Programming Language :: Python :: 3.4
Classifier: Programming Language :: Python :: 3.5
Classifier: Programming Language :: Python :: 3.6
Classifier: Programming Language :: Python :: 3.7
Requires-Python: >=2.6, !=3.0.*, !=3.1.*, !=3.2.*, <4
